geoengineer/__init__.py
geoengineer/soil_mechanics.py
geoengineer/version.py
geoengineer/tests/__init__.py
geoengineer/tests/test_soil_mechanics.py
geoengineer-0.1.2.dist-info/LICENSE
geoengineer-0.1.2.dist-info/METADATA
geoengineer-0.1.2.dist-info/WHEEL
geoengineer-0.1.2.dist-info/top_level.txt
geoengineer-0.1.2.dist-info/RECORD
