Metadata-Version: 2.2
Name: geoengineer
Version: 0.1.2
Summary: The official Python library for the GeoEngineerAI API
Home-page: https://github.com/geoengineer-ai/geoengineer-python
Author: GeoEngineer Contributors
Author-email: GeoEngineer Contributors <geoengineerai@gmail.com>
License: MIT
Project-URL: Homepage, https://github.com/geoengineer-ai/geoengineer-python
Project-URL: Bug Tracker, https://github.com/geoengineer-ai/geoengineer-python/issues
Classifier: Programming Language :: Python :: 3
Classifier: License :: OSI Approved :: MIT License
Classifier: Operating System :: OS Independent
Classifier: Topic :: Scientific/Engineering
Requires-Python: >=3.6
License-File: LICENSE
Dynamic: author
Dynamic: home-page
Dynamic: requires-python
